superserve/__init__.py
superserve/agent_base.py
superserve/base.py
superserve/batch.py
superserve/decorators.py
superserve/deployment.py
superserve/mcp_serve.py
superserve/resource_loader.py
superserve/serve.py
superserve/utils.py
superserve/cli/__init__.py
superserve/cli/analytics.py
superserve/cli/cli.py
superserve/cli/commands/__init__.py
superserve/cli/commands/analytics.py
superserve/cli/commands/create_agent.py
superserve/cli/commands/create_mcp.py
superserve/cli/commands/delete.py
superserve/cli/commands/deploy.py
superserve/cli/commands/init.py
superserve/cli/commands/login.py
superserve/cli/commands/logout.py
superserve/cli/commands/logs.py
superserve/cli/commands/status.py
superserve/cli/commands/up.py
superserve/cli/commands/mcp/__init__.py
superserve/cli/commands/mcp/up.py
superserve/cli/platform/__init__.py
superserve/cli/platform/auth.py
superserve/cli/platform/client.py
superserve/cli/platform/config.py
superserve/cli/platform/packaging.py
superserve/cli/platform/types.py
superserve/cli/templates/__init__.py
superserve/cli/templates/__pycache__/__init__.cpython-312.pyc
superserve/cli/templates/agent/.env.example
superserve/cli/templates/agent/README.md
superserve/cli/templates/agent/__init__.py
superserve/cli/templates/agent/pyproject.toml
superserve/cli/templates/agent/agents/.gitkeep
superserve/examples/__init__.py
superserve/sandbox/__init__.py
superserve/sandbox/backend.py
superserve/sandbox/config.py
superserve/sandbox/executor.py
superserve/sandbox/kubernetes_executor.py
superserve/sandbox/mcp_proxy.py
superserve/sandbox/sandbox.py
superserve/sandbox/tools.py
superserve/sandbox/types.py
superserve-0.1.2.dist-info/licenses/LICENSE
superserve-0.1.2.dist-info/METADATA
superserve-0.1.2.dist-info/WHEEL
superserve-0.1.2.dist-info/entry_points.txt
superserve-0.1.2.dist-info/top_level.txt
superserve-0.1.2.dist-info/RECORD
