Metadata-Version: 2.4
Name: superserve
Version: 0.1.2
Summary: Run agentic workloads on Ray
License:                                  Apache License
Project-URL: Homepage, https://superserve.ai
Project-URL: Repository, https://github.com/superserve-ai/agentic-ray
Keywords: ray,agents,ai,llm,distributed,pydantic-ai,langchain,parallel tool call
Requires-Python: >=3.12
License-File: LICENSE
Requires-Dist: langchain>=1.0.0
Requires-Dist: langchain-openai>=1.0.0
Requires-Dist: langgraph>=0.6.10
Requires-Dist: openai>=1.0.0
Requires-Dist: python-dotenv>=1.0.0
Requires-Dist: fastapi>=0.100.0
Requires-Dist: click>=8.0.0
Requires-Dist: pydantic-ai-slim[openai]>=1.42.0
Requires-Dist: anyio>=4.0
Requires-Dist: posthog>=3.0.0
Requires-Dist: ray[serve]
Provides-Extra: sandbox
Requires-Dist: docker>=7.0.0; extra == "sandbox"
Requires-Dist: requests>=2.31.0; extra == "sandbox"
Dynamic: license-file
